midi_websocket_server/__init__.py
midi_websocket_server/__main__.py
midi_websocket_server/midi_helpers.py
midi_websocket_server/midi_websocket_server.py
midi_websocket_server-1.0.0.dist-info/LICENSE
midi_websocket_server-1.0.0.dist-info/METADATA
midi_websocket_server-1.0.0.dist-info/WHEEL
midi_websocket_server-1.0.0.dist-info/top_level.txt
midi_websocket_server-1.0.0.dist-info/RECORD
