Metadata-Version: 2.1
Name: midi-websocket-server
Version: 1.0.0
Summary: Python Websocket server to facilitate two-way communication with all connected MIDI devices.
Home-page: https://github.com/PeterSR/python-midi-websocket-server
Author: Peter Severin Rasmussen
Author-email: git@petersr.com
License: MIT
Platform: UNKNOWN
Classifier: License :: OSI Approved :: MIT License
Classifier: Programming Language :: Python :: 3.7
Requires-Python: >=3.7
Requires-Dist: websockets (>=8.1)
Requires-Dist: python-rtmidi (>=1.4.0)
